qaekwy/__init__.py
qaekwy/__main__.py
qaekwy/__metadata__.py
qaekwy/api/__init__.py
qaekwy/api/exceptions.py
qaekwy/api/model.py
qaekwy/core/__init__.py
qaekwy/core/engine.py
qaekwy/core/explanation.py
qaekwy/core/response.py
qaekwy/core/solution.py
qaekwy/core/exception/__init__.py
qaekwy/core/exception/model_failure.py
qaekwy/core/model/__init__.py
qaekwy/core/model/cutoff.py
qaekwy/core/model/function.py
qaekwy/core/model/modeller.py
qaekwy/core/model/searcher.py
qaekwy/core/model/specific.py
qaekwy/core/model/constraint/__init__.py
qaekwy/core/model/constraint/abs.py
qaekwy/core/model/constraint/abstract_constraint.py
qaekwy/core/model/constraint/acos.py
qaekwy/core/model/constraint/asin.py
qaekwy/core/model/constraint/atan.py
qaekwy/core/model/constraint/cos.py
qaekwy/core/model/constraint/distinct.py
qaekwy/core/model/constraint/divide.py
qaekwy/core/model/constraint/element.py
qaekwy/core/model/constraint/exponential.py
qaekwy/core/model/constraint/if_then_else.py
qaekwy/core/model/constraint/logarithm.py
qaekwy/core/model/constraint/maximum.py
qaekwy/core/model/constraint/member.py
qaekwy/core/model/constraint/minimum.py
qaekwy/core/model/constraint/modulo.py
qaekwy/core/model/constraint/multiply.py
qaekwy/core/model/constraint/nroot.py
qaekwy/core/model/constraint/power.py
qaekwy/core/model/constraint/relational.py
qaekwy/core/model/constraint/sin.py
qaekwy/core/model/constraint/sort.py
qaekwy/core/model/constraint/tan.py
qaekwy/core/model/variable/__init__.py
qaekwy/core/model/variable/boolean.py
qaekwy/core/model/variable/branch.py
qaekwy/core/model/variable/float.py
qaekwy/core/model/variable/integer.py
qaekwy/core/model/variable/variable.py
qaekwy-0.3.1.dist-info/licenses/LICENSE
qaekwy-0.3.1.dist-info/METADATA
qaekwy-0.3.1.dist-info/WHEEL
qaekwy-0.3.1.dist-info/top_level.txt
qaekwy-0.3.1.dist-info/RECORD
