Metadata-Version: 2.4
Name: qaekwy
Version: 0.3.1
Summary: Qaekwy, a modern, open-source Python framework for declarative constraint programming and combinatorial optimization
Author-email: Alexis LE GOADEC <alex@qaekwy.io>
License-Expression: EUPL-1.2
Project-URL: Homepage, https://qaekwy.io
Project-URL: Documentation, https://docs.qaekwy.io
Project-URL: Issue Tracker, https://github.com/alex-87/qaekwy-python/issues
Project-URL: Source, https://github.com/alex-87/qaekwy-python
Keywords: optimization,constraint programming,combinatorial optimization,operations research,constraint satisfaction,constraint solver,solver,CSP,optimization library,optimization framework,mathematical optimization,discrete optimization,optimization modeling,constraint modeling,declarative programming,modeling language,DSL,define-and-solve,scheduling,routing,planning,resource allocation,assignment,decision support,open source,Python
Classifier: Development Status :: 4 - Beta
Classifier: Intended Audience :: Developers
Classifier: Intended Audience :: Education
Classifier: Intended Audience :: Science/Research
Classifier: Programming Language :: Python
Classifier: Programming Language :: Python :: 3
Classifier: Topic :: Scientific/Engineering
Classifier: Topic :: Scientific/Engineering :: Mathematics
Classifier: Topic :: Scientific/Engineering :: Artificial Intelligence
Classifier: Topic :: Software Development :: Libraries :: Python Modules
Requires-Python: >=3.9
License-File: LICENSE
Requires-Dist: requests
Provides-Extra: types
Requires-Dist: types-requests; extra == "types"
Provides-Extra: dev
Requires-Dist: pytest>=7.0; extra == "dev"
Requires-Dist: pytest-cov; extra == "dev"
Requires-Dist: black; extra == "dev"
Requires-Dist: mypy; extra == "dev"
Requires-Dist: pylint; extra == "dev"
Requires-Dist: build; extra == "dev"
Requires-Dist: twine; extra == "dev"
Dynamic: license-file
